CHANGELOG.md
MANIFEST.in
README.md
TODO.txt
requirements.txt
setup.py
./benchmarks/2d_convolution.py
./benchmarks/__init__.py
./benchmarks/allpairs_distances.py
./benchmarks/arc_distance.py
./benchmarks/collatz.py
./benchmarks/compare_perf.py
./benchmarks/diffuse.py
./benchmarks/finite-difference.py
./benchmarks/growcut.py
./benchmarks/harris.py
./benchmarks/julia.py
./benchmarks/kmeans.py
./benchmarks/matmult.py
./benchmarks/matmult_tropical.py
./benchmarks/morphology.py
./benchmarks/nd_local_maxima.py
./benchmarks/periodic_dist.py
./benchmarks/pulseprop.py
./benchmarks/rosenbrock.py
./benchmarks/simple_conv.py
./benchmarks/simple_regression.py
./benchmarks/smoothing.py
./benchmarks/sph_render.py
./benchmarks/summation.py
./benchmarks/template_sph_render.py
./benchmarks/tensor_rotation.py
./benchmarks/timer.py
./benchmarks/wald.py
./examples/__init__.py
./examples/convolution.py
./examples/finite-difference.py
./examples/growcut.py
./examples/kmeans.py
./examples/matmult.py
./examples/rosenbrock.py
./examples/simple_avg.py
./examples/simple_regression.py
./examples/sum_loop.py
./examples/tensor_rotation.py
./test/__init__.py
benchmarks/2d_convolution.py
benchmarks/__init__.py
benchmarks/allpairs_distances.py
benchmarks/arc_distance.py
benchmarks/collatz.py
benchmarks/compare_perf.py
benchmarks/diffuse.py
benchmarks/finite-difference.py
benchmarks/growcut.py
benchmarks/harris.py
benchmarks/julia.py
benchmarks/kmeans.py
benchmarks/matmult.py
benchmarks/matmult_tropical.py
benchmarks/morphology.py
benchmarks/nd_local_maxima.py
benchmarks/periodic_dist.py
benchmarks/pulseprop.py
benchmarks/rosenbrock.py
benchmarks/simple_conv.py
benchmarks/simple_regression.py
benchmarks/smoothing.py
benchmarks/sph_render.py
benchmarks/summation.py
benchmarks/template_sph_render.py
benchmarks/tensor_rotation.py
benchmarks/timer.py
benchmarks/wald.py
examples/__init__.py
examples/convolution.py
examples/finite-difference.py
examples/growcut.py
examples/kmeans.py
examples/matmult.py
parakeet.egg-info/PKG-INFO
parakeet.egg-info/SOURCES.txt
parakeet.egg-info/dependency_links.txt
parakeet.egg-info/requires.txt
parakeet.egg-info/top_level.txt
