Metadata-Version: 1.1
Name: parakeet
Version: 0.24
Summary: Runtime compiler for numerical Python.
Home-page: UNKNOWN
Author: Alex Rubinsteyn
Author-email: alexr@cs.nyu.edu
License: BSD
Download-URL: https://github.com/iskandr/parakeet/releases
Platform: UNKNOWN
Classifier: Development Status :: 3 - Alpha
Classifier: Topic :: Software Development :: Libraries
Classifier: License :: OSI Approved :: BSD License
Classifier: Intended Audience :: Developers
Classifier: Programming Language :: Python :: 2.7
